Metadata-Version: 2.1
Name: colabshell
Version: 0.1.0
Summary: ColabShell - Run shell on Colab/Kaggle notebook!
Home-page: https://github.com/sandyz1000/colabshell
Author: Sandip Dey
Author-email: sandip.dey1988@yahoo.com
License: MIT License
Platform: linux
Platform: unix
Requires-Python: >=3.5
